package pkg;

import java.lang.annotation.ElementType;
import java.util.Scanner;

public class TestTryWithResourcesAfterSwitch {
   public void test() {
      ElementType vvv3 = ElementType.METHOD;// 8
      if (vvv3 != null) {// 9
         throw new RuntimeException();// 10
      } else {
         String vvv25 = "default";// 14
         switch(vvv25) {
            case "HYxSY":
            default:
               ElementType vvv25x = ElementType.METHOD;// 19

               try (Scanner vvv26 = new Scanner(System.in)) {// 20
                  System.out.println("hi");// 21
               } finally {
                  System.out.println("f");// 23
               }
         }
      }
   }// 24

   public void test2() {
      // $VF: Couldn't be decompiled
      // Bytecode:
      // 00: getstatic java/lang/annotation/ElementType.METHOD Ljava/lang/annotation/ElementType;
      // 03: astore 1
      // 04: aload 1
      // 05: ifnull 10
      // 08: new java/lang/RuntimeException
      // 0b: dup
      // 0c: invokespecial java/lang/RuntimeException.<init> ()V
      // 0f: athrow
      // 10: ldc "default"
      // 12: astore 2
      // 13: bipush -1
      // 14: istore 3
      // 15: aload 2
      // 16: invokevirtual java/lang/String.hashCode ()I
      // 19: lookupswitch 30 1 69262893 19
      // 2c: aload 2
      // 2d: ldc "HYxSY"
      // 2f: invokevirtual java/lang/String.equals (Ljava/lang/Object;)Z
      // 32: ifeq 37
      // 35: bipush 0
      // 36: istore 3
      // 37: iload 3
      // 38: lookupswitch 20 1 0 20
      // 4c: new java/util/Scanner
      // 4f: dup
      // 50: getstatic java/lang/System.in Ljava/io/InputStream;
      // 53: invokespecial java/util/Scanner.<init> (Ljava/io/InputStream;)V
      // 56: astore 2
      // 57: aconst_null
      // 58: astore 3
      // 59: getstatic java/lang/System.out Ljava/io/PrintStream;
      // 5c: ldc "hi"
      // 5e: invokevirtual java/io/PrintStream.println (Ljava/lang/String;)V
      // 61: aload 2
      // 62: ifnull ad
      // 65: aload 3
      // 66: ifnull 7b
      // 69: aload 2
      // 6a: invokevirtual java/util/Scanner.close ()V
      // 6d: goto ad
      // 70: astore 4
      // 72: aload 3
      // 73: aload 4
      // 75: invokevirtual java/lang/Throwable.addSuppressed (Ljava/lang/Throwable;)V
      // 78: goto ad
      // 7b: aload 2
      // 7c: invokevirtual java/util/Scanner.close ()V
      // 7f: goto ad
      // 82: astore 4
      // 84: aload 4
      // 86: astore 3
      // 87: aload 4
      // 89: athrow
      // 8a: astore 5
      // 8c: aload 2
      // 8d: ifnull aa
      // 90: aload 3
      // 91: ifnull a6
      // 94: aload 2
      // 95: invokevirtual java/util/Scanner.close ()V
      // 98: goto aa
      // 9b: astore 6
      // 9d: aload 3
      // 9e: aload 6
      // a0: invokevirtual java/lang/Throwable.addSuppressed (Ljava/lang/Throwable;)V
      // a3: goto aa
      // a6: aload 2
      // a7: invokevirtual java/util/Scanner.close ()V
      // aa: aload 5
      // ac: athrow
      // ad: getstatic java/lang/System.out Ljava/io/PrintStream;
      // b0: ldc "f"
      // b2: invokevirtual java/io/PrintStream.println (Ljava/lang/String;)V
      // b5: goto c5
      // b8: astore 7
      // ba: getstatic java/lang/System.out Ljava/io/PrintStream;
      // bd: ldc "f"
      // bf: invokevirtual java/io/PrintStream.println (Ljava/lang/String;)V
      // c2: aload 7
      // c4: athrow
      // c5: return
   }
}

class 'pkg/TestTryWithResourcesAfterSwitch' {
   method 'test ()V' {
      0      7
      1      7
      2      7
      3      7
      4      8
      5      8
      f      9
      10      11
      11      11
      12      11
      15      12
      2d      13
      2e      13
      38      12
      4c      15
      4d      15
      4e      15
      4f      15
      54      17
      55      17
      56      17
      5a      17
      5e      18
      5f      18
      60      18
      61      18
      62      18
      63      18
      bf      24
      c4      20
      c5      20
      c6      20
      c7      20
      c8      20
      c9      20
   }
}

Lines mapping:
8 <-> 8
9 <-> 9
10 <-> 10
14 <-> 12
19 <-> 16
20 <-> 18
21 <-> 19
23 <-> 21
24 <-> 25
Not mapped:
22
25
