package pkg;

import ext.Direction;

public class TestSwitchExpressionNested1 {
   public int test(Direction dir, Direction dir2) {
      // $FF: Couldn't be decompiled
      // Bytecode:
      // 00: getstatic pkg/TestSwitchExpressionNested1$1.$SwitchMap$ext$Direction [I
      // 03: aload 1
      // 04: invokevirtual ext/Direction.ordinal ()I
      // 07: iaload
      // 08: tableswitch 88 1 3 28 32 36
      // 24: bipush 1
      // 25: goto 61
      // 28: bipush 2
      // 29: goto 61
      // 2c: getstatic pkg/TestSwitchExpressionNested1$1.$SwitchMap$ext$Direction [I
      // 2f: aload 2
      // 30: invokevirtual ext/Direction.ordinal ()I
      // 33: iaload
      // 34: tableswitch 40 1 3 28 32 36
      // 50: bipush 3
      // 51: goto 61
      // 54: bipush 4
      // 55: goto 61
      // 58: bipush 5
      // 59: goto 61
      // 5c: bipush 1
      // 5d: goto 61
      // 60: bipush 0
      // 61: ireturn
   }
}

