package pkg;

import java.io.IOException;
import java.net.InetSocketAddress;
import java.net.SocketAddress;
import java.net.StandardProtocolFamily;
import java.net.UnixDomainSocketAddress;
import java.nio.channels.SocketChannel;
import java.nio.channels.UnsupportedAddressTypeException;
import java.util.Objects;

public class TestTryWithResourcesFake {
   public static SocketChannel open(SocketAddress param0) throws IOException {
      // $FF: Couldn't be decompiled
      // java.lang.IndexOutOfBoundsException: Index: 1, Size: 1
      //   at java.util.ArrayList.rangeCheck(ArrayList.java:659)
      //   at java.util.ArrayList.get(ArrayList.java:435)
      //   at org.jetbrains.java.decompiler.util.VBStyleCollection.remove(VBStyleCollection.java:102)
      //   at org.jetbrains.java.decompiler.modules.decompiler.TryWithResourcesProcessor.makeTryWithResourceJ11(TryWithResourcesProcessor.java:197)
      //   at org.jetbrains.java.decompiler.modules.decompiler.TryHelper.makeTryWithResourceRec(TryHelper.java:42)
      //   at org.jetbrains.java.decompiler.modules.decompiler.TryHelper.makeTryWithResourceRec(TryHelper.java:55)
      //   at org.jetbrains.java.decompiler.modules.decompiler.TryHelper.makeTryWithResourceRec(TryHelper.java:55)
      //   at org.jetbrains.java.decompiler.modules.decompiler.TryHelper.enhanceTryStats(TryHelper.java:18)
      //   at org.jetbrains.java.decompiler.main.rels.MethodProcessorRunnable.codeToJava(MethodProcessorRunnable.java:265)
      //
      // Bytecode:
      // 00: aload 0
      // 01: invokestatic java/util/Objects.requireNonNull (Ljava/lang/Object;)Ljava/lang/Object;
      // 04: pop
      // 05: aload 0
      // 06: instanceof java/net/InetSocketAddress
      // 09: ifeq 13
      // 0c: invokestatic java/nio/channels/SocketChannel.open ()Ljava/nio/channels/SocketChannel;
      // 0f: astore 1
      // 10: goto 2c
      // 13: aload 0
      // 14: instanceof java/net/UnixDomainSocketAddress
      // 17: ifeq 24
      // 1a: getstatic java/net/StandardProtocolFamily.UNIX Ljava/net/StandardProtocolFamily;
      // 1d: invokestatic java/nio/channels/SocketChannel.open (Ljava/net/ProtocolFamily;)Ljava/nio/channels/SocketChannel;
      // 20: astore 1
      // 21: goto 2c
      // 24: new java/nio/channels/UnsupportedAddressTypeException
      // 27: dup
      // 28: invokespecial java/nio/channels/UnsupportedAddressTypeException.<init> ()V
      // 2b: athrow
      // 2c: aload 1
      // 2d: aload 0
      // 2e: invokevirtual java/nio/channels/SocketChannel.connect (Ljava/net/SocketAddress;)Z
      // 31: pop
      // 32: goto 45
      // 35: astore 2
      // 36: aload 1
      // 37: invokevirtual java/nio/channels/SocketChannel.close ()V
      // 3a: goto 43
      // 3d: astore 3
      // 3e: aload 2
      // 3f: aload 3
      // 40: invokevirtual java/lang/Throwable.addSuppressed (Ljava/lang/Throwable;)V
      // 43: aload 2
      // 44: athrow
      // 45: getstatic pkg/TestTryWithResourcesFake.$assertionsDisabled Z
      // 48: ifne 5a
      // 4b: aload 1
      // 4c: invokevirtual java/nio/channels/SocketChannel.isConnected ()Z
      // 4f: ifne 5a
      // 52: new java/lang/AssertionError
      // 55: dup
      // 56: invokespecial java/lang/AssertionError.<init> ()V
      // 59: athrow
      // 5a: aload 1
      // 5b: areturn
   }
}

