package pkg;

public class TestSwitchPatternMatching19 {
   static void test(TestSwitchPatternMatching19.XXX var0) {
      // $VF: Couldn't be decompiled
      // Bytecode:
      // 00: aload 0
      // 01: astore 1
      // 02: bipush 0
      // 03: istore 2
      // 04: aload 1
      // 05: iload 2
      // 06: invokedynamic enumSwitch (Lpkg/TestSwitchPatternMatching19$XXX;I)I bsm=java/lang/runtime/SwitchBootstraps.enumSwitch (Ljava/lang/invoke/MethodHandles$Lookup;Ljava/lang/String;Ljava/lang/invoke/MethodType;[Ljava/lang/Object;)Ljava/lang/invoke/CallSite; args=[ "X1", pkg/TestSwitchPatternMatching19$XXX, pkg/TestSwitchPatternMatching19$XXX, pkg/TestSwitchPatternMatching19$XXX, pkg/TestSwitchPatternMatching19$XXX, pkg/TestSwitchPatternMatching19$XXX ]
      // 0b: tableswitch 134 -1 4 134 37 48 73 100 126
      // 30: getstatic java/lang/System.out Ljava/io/PrintStream;
      // 33: ldc "x1"
      // 35: invokevirtual java/io/PrintStream.println (Ljava/lang/String;)V
      // 38: goto 9f
      // 3b: aload 1
      // 3c: astore 3
      // 3d: aload 3
      // 3e: getstatic pkg/TestSwitchPatternMatching19$XXX.X1 Lpkg/TestSwitchPatternMatching19$XXX;
      // 41: if_acmpne 49
      // 44: bipush 2
      // 45: istore 2
      // 46: goto 04
      // 49: getstatic java/lang/System.out Ljava/io/PrintStream;
      // 4c: ldc "a"
      // 4e: invokevirtual java/io/PrintStream.println (Ljava/lang/String;)V
      // 51: goto 9f
      // 54: aload 1
      // 55: astore 4
      // 57: aload 4
      // 59: instanceof pkg/TestSwitchPatternMatching19$C
      // 5c: ifne 64
      // 5f: bipush 3
      // 60: istore 2
      // 61: goto 04
      // 64: getstatic java/lang/System.out Ljava/io/PrintStream;
      // 67: ldc "b"
      // 69: invokevirtual java/io/PrintStream.println (Ljava/lang/String;)V
      // 6c: goto 9f
      // 6f: aload 1
      // 70: astore 5
      // 72: aload 5
      // 74: aload 5
      // 76: if_acmpeq 7e
      // 79: bipush 4
      // 7a: istore 2
      // 7b: goto 04
      // 7e: getstatic java/lang/System.out Ljava/io/PrintStream;
      // 81: ldc "d"
      // 83: invokevirtual java/io/PrintStream.println (Ljava/lang/String;)V
      // 86: goto 9f
      // 89: aload 1
      // 8a: astore 6
      // 8c: bipush 5
      // 8d: istore 2
      // 8e: goto 04
      // 91: aload 1
      // 92: astore 7
      // 94: getstatic java/lang/System.out Ljava/io/PrintStream;
      // 97: ldc "f"
      // 99: invokevirtual java/io/PrintStream.println (Ljava/lang/String;)V
      // 9c: goto 9f
      // 9f: return
   }

   static void test2(TestSwitchPatternMatching19.XXX s) {
      switch (s) {// 16
         case X2:
         case null:
            System.out.println("maybe x2?");// 18
            break;
         case X1:
            System.out.println("x1");// 17
            break;
         case TestSwitchPatternMatching19.XXX var4 when Math.random() > 0.0:// 19
            System.out.println("just making sure!");// 20
            break;
         default:
            System.out.println("default");// 21
      }
   }// 23

   interface A {
   }

   interface B {
   }

   interface C {
   }

   interface D {
   }

   interface E {
   }

   interface F {
   }

   enum XXX
      implements TestSwitchPatternMatching19.A,
      TestSwitchPatternMatching19.B,
      TestSwitchPatternMatching19.C,
      TestSwitchPatternMatching19.D,
      TestSwitchPatternMatching19.E,
      TestSwitchPatternMatching19.F {
      X1,
      X2,
      X3;
   }
}

class 'pkg/TestSwitchPatternMatching19' {
   method 'test2 (Lpkg/TestSwitchPatternMatching19$XXX;)V' {
      0      69
      b      69
      c      69
      d      69
      e      69
      f      69
      10      69
      11      69
      12      69
      13      69
      14      69
      15      69
      16      69
      17      69
      18      69
      19      69
      1a      69
      1b      69
      1c      69
      1d      69
      1e      69
      1f      69
      20      69
      21      69
      22      69
      23      69
      24      69
      25      69
      26      69
      27      69
      28      75
      29      75
      2a      75
      2b      75
      2c      75
      2d      75
      2e      75
      2f      75
      30      76
      33      72
      34      72
      35      72
      36      72
      37      72
      38      72
      39      72
      3a      72
      3b      73
      40      77
      41      77
      42      77
      43      77
      44      77
      4d      78
      4e      78
      4f      78
      50      78
      51      78
      52      78
      53      78
      54      78
      55      79
      58      81
      59      81
      5a      81
      5b      81
      5c      81
      5d      81
      5e      81
      5f      81
      63      83
   }
}

Lines mapping:
16 <-> 70
17 <-> 76
18 <-> 73
19 <-> 78
20 <-> 79
21 <-> 82
23 <-> 84