package pkg;

class TestSwitchPatternMatchingFuzz1 {
   public void test() {
      // $QF: Couldn't be decompiled
      // Bytecode:
      // 00: new java/lang/Object
      // 03: dup
      // 04: invokespecial java/lang/Object.<init> ()V
      // 07: astore 1
      // 08: bipush 0
      // 09: istore 2
      // 0a: aload 1
      // 0b: iload 2
      // 0c: invokedynamic typeSwitch (Ljava/lang/Object;I)I bsm=java/lang/runtime/SwitchBootstraps.typeSwitch (Ljava/lang/invoke/MethodHandles$Lookup;Ljava/lang/String;Ljava/lang/invoke/MethodType;[Ljava/lang/Object;)Ljava/lang/invoke/CallSite; args=[ java/lang/Double ]
      // 11: lookupswitch 27 2 -1 35 0 35
      // 2c: new java/lang/RuntimeException
      // 2f: dup
      // 30: invokespecial java/lang/RuntimeException.<init> ()V
      // 33: athrow
      // 34: aload 1
      // 35: checkcast java/lang/Double
      // 38: astore 3
      // 39: bipush 0
      // 3a: newarray 11
      // 3c: astore 4
      // 3e: aload 4
      // 40: arraylength
      // 41: istore 5
      // 43: bipush 0
      // 44: istore 6
      // 46: iload 6
      // 48: iload 5
      // 4a: if_icmpge 5c
      // 4d: aload 4
      // 4f: iload 6
      // 51: laload
      // 52: lstore 7
      // 54: new java/lang/RuntimeException
      // 57: dup
      // 58: invokespecial java/lang/RuntimeException.<init> ()V
      // 5b: athrow
      // 5c: getstatic java/lang/System.out Ljava/io/PrintStream;
      // 5f: ldc "Hi"
      // 61: invokevirtual java/io/PrintStream.println (Ljava/lang/String;)V
      // 64: return
      // 65: astore 1
      // 66: goto 6e
      // 69: astore 9
      // 6b: aload 9
      // 6d: athrow
      // 6e: new java/lang/RuntimeException
      // 71: dup
      // 72: invokespecial java/lang/RuntimeException.<init> ()V
      // 75: athrow
   }
}

