package pkg;

import java.util.Random;
import java.util.function.Supplier;

public class TestTryReturn {
   public boolean test(Supplier<Boolean> supplier) {
      try {
         return supplier.get();// 9
      } catch (Exception var3) {// 10
         throw new RuntimeException(var3);// 11
      }
   }

   public boolean testFinally(Supplier<Boolean> supplier) {
      try {
         return supplier.get();// 17
      } finally {
         System.out.println("Finally");// 19
      }
   }

   public void testFinally1(Supplier<Boolean> supplier) {
      System.out.println("pred");// 24

      label27: {
         try {
            if (!supplier.get()) {// 27
               break label27;
            }
         } finally {
            System.out.println("Finally");// 31
         }

         return;// 28
      }

      System.out.println("suc");// 34
   }// 35

   public boolean testFinally2(Supplier<Boolean> supplier) {
      boolean b;
      try {
         b = supplier.get();// 40
      } finally {
         System.out.println("Finally");// 42
      }

      return b;// 45
   }

   public boolean testFinally3(boolean b, boolean c, int a, Supplier<Boolean> supplier) {
      try {
         if (!b) {// 50
            return a > 0 ? a == 1 : supplier.get();// 54 55 58
         } else {
            return c && supplier.get();// 51
         }
      } finally {
         System.out.println("Finally");// 60
      }
   }

   public boolean testFinally4(Supplier<Boolean> supplier) {
      boolean b = false;// 65

      try {
         b = supplier.get();// 67
      } finally {
         System.out.println("Finally");// 69
      }

      return b;// 72
   }

   public boolean testFinally5(Supplier<Boolean> supplier) {
      boolean b = false;// 76

      try {
         b = supplier.get();// 78
      } catch (Exception e) {// 79
         System.out.println("Catch");// 80
         b = supplier.get();// 81
      } finally {
         System.out.println("Finally");// 83
      }

      return b;// 86
   }

   public boolean testFinally6(boolean a, Supplier<Boolean> supplier) {
      boolean b = false;// 90

      try {
         if (a) {// 92
            b = true;// 93
            System.out.println("If");// 94
         }

         b = supplier.get();// 97
      } catch (Exception e) {// 98
         System.out.println("Catch");// 99
         b = supplier.get();// 100
      } finally {
         System.out.println("Finally");// 102
      }

      return b;// 105
   }

   public void testLoopFinally() {
      boolean a = true;// 109

      while (true) {
         try {
            if (a) {// 113
               return;// 114
            }
         } finally {
            System.out.println("Finally");// 117
         }
      }
   }

   public void testParsingFailure() {
      // $VF: Couldn't be decompiled
      // Bytecode:
      // 00: bipush 116
      // 02: istore 1
      // 03: iload 1
      // 04: bipush 113
      // 06: if_icmpeq 2a
      // 09: getstatic java/lang/System.out Ljava/io/PrintStream;
      // 0c: iload 1
      // 0d: invokevirtual java/io/PrintStream.println (C)V
      // 10: getstatic java/lang/System.out Ljava/io/PrintStream;
      // 13: iload 1
      // 14: invokevirtual java/io/PrintStream.println (C)V
      // 17: return
      // 18: astore 2
      // 19: getstatic java/lang/System.out Ljava/io/PrintStream;
      // 1c: iload 1
      // 1d: invokevirtual java/io/PrintStream.println (C)V
      // 20: return
      // 21: astore 3
      // 22: getstatic java/lang/System.out Ljava/io/PrintStream;
      // 25: iload 1
      // 26: invokevirtual java/io/PrintStream.println (C)V
      // 29: return
      // 2a: getstatic java/lang/System.out Ljava/io/PrintStream;
      // 2d: iload 1
      // 2e: invokevirtual java/io/PrintStream.println (C)V
      // 31: return
      // 32: astore 4
      // 34: getstatic java/lang/System.out Ljava/io/PrintStream;
      // 37: iload 1
      // 38: invokevirtual java/io/PrintStream.println (C)V
      // 3b: return
      // try (5 -> 8): 12 java/lang/Exception
      // try (5 -> 8): 17 null
      // try (2 -> 8): 26 null
      // try (26 -> 27): 26 null
   }

   public void testParsingFailureSimple() {
      // $VF: Couldn't be decompiled
      // Bytecode:
      // 00: getstatic java/lang/System.out Ljava/io/PrintStream;
      // 03: ldc "inner"
      // 05: invokevirtual java/io/PrintStream.println (Ljava/lang/String;)V
      // 08: getstatic java/lang/System.out Ljava/io/PrintStream;
      // 0b: ldc "fin"
      // 0d: invokevirtual java/io/PrintStream.println (Ljava/lang/String;)V
      // 10: return
      // 11: astore 1
      // 12: getstatic java/lang/System.out Ljava/io/PrintStream;
      // 15: ldc "fin"
      // 17: invokevirtual java/io/PrintStream.println (Ljava/lang/String;)V
      // 1a: return
      // 1b: astore 2
      // 1c: getstatic java/lang/System.out Ljava/io/PrintStream;
      // 1f: ldc "fin"
      // 21: invokevirtual java/io/PrintStream.println (Ljava/lang/String;)V
      // 24: aload 2
      // 25: athrow
      // try (0 -> 3): 7 null
      // try (0 -> 3): 12 null
   }

   public void testPostdomFailure() {
      System.out.println(1);// 155

      while (new Random().nextBoolean()) {// 157
         try {
            try {
               System.out.println(2);// 160
            } catch (Exception var9) {// 161
               System.out.println(3);// 162
            } finally {
               continue;
            }
         } finally {
            byte var7 = 28;// 168
         }
      }
   }// 171

   public void testVarWrong() {
      try {
         System.out.println("Hi");// 176
         return;// 187
      } catch (Exception var2) {// 177
         if (var2 == null) {// 178
            System.out.println(var2);// 181
            return;// 182
         }
      } finally {
         float var5 = 9.18F;// 185
      }
   }// 179

   public void testInvalidUse() {
      boolean var1 = false;// 190
      String var3 = "Hi!";// 191

      try {
         Exception var4;
         try {
            System.out.println(var1);// 193
            return;// 194
         } catch (Exception var15) {// 195
            var4 = var15;
         }

         try {
            System.out.println(var4);// 197
            return;// 208
         } catch (Exception var5) {// 198
         } finally {
            System.out.println(var15);// 202
         }
      } finally {
         System.out.println(var3);// 206
      }
   }// 199

   public void returnInCatch() {
      label27: {
         try {
            System.out.println("Hi!");// 212
            break label27;
         } catch (Exception e) {// 213
            System.out.println("hello");// 214
         } finally {
            System.out.println("finally");// 217
         }

         return;// 215
      }

      System.out.println("post");// 220
   }// 221
}

class 'pkg/TestTryReturn' {
   method 'test (Ljava/util/function/Supplier;)Z' {
      0      8
      1      8
      2      8
      3      8
      4      8
      5      8
      9      8
      a      8
      b      8
      c      8
      d      9
      12      10
      16      10
   }

   method 'testFinally (Ljava/util/function/Supplier;)Z' {
      0      16
      1      16
      2      16
      3      16
      4      16
      5      16
      9      16
      a      16
      b      16
      16      16
      18      18
      19      18
      1a      18
      1b      18
      1c      18
      1d      18
      1e      18
      1f      18
   }

   method 'testFinally1 (Ljava/util/function/Supplier;)V' {
      0      23
      1      23
      2      23
      3      23
      4      23
      5      23
      6      23
      7      23
      8      27
      9      27
      a      27
      b      27
      c      27
      d      27
      11      27
      12      27
      13      27
      14      27
      15      27
      16      27
      1f      34
      2c      31
      2d      31
      2e      31
      2f      31
      30      31
      31      31
      32      31
      33      31
      36      37
      37      37
      38      37
      39      37
      3a      37
      3b      37
      3c      37
      3d      37
      3e      38
   }

   method 'testFinally2 (Ljava/util/function/Supplier;)Z' {
      0      43
      1      43
      2      43
      3      43
      4      43
      5      43
      9      43
      a      43
      b      43
      c      43
      19      45
      1a      45
      1b      45
      1c      45
      1d      45
      1e      45
      1f      45
      20      45
      23      48
      24      48
   }

   method 'testFinally3 (ZZILjava/util/function/Supplier;)Z' {
      0      53
      1      53
      2      53
      3      53
      4      56
      5      56
      6      56
      7      56
      8      56
      9      56
      a      56
      b      56
      c      56
      d      56
      e      56
      12      56
      13      56
      14      56
      15      56
      16      56
      17      56
      29      56
      2a      54
      2b      54
      2c      54
      2d      54
      2e      54
      2f      54
      30      54
      31      54
      32      54
      45      54
      46      54
      47      54
      48      54
      49      54
      4a      54
      4b      54
      4f      54
      50      54
      51      54
      61      59
      62      59
      63      59
      64      59
      65      59
      66      59
      67      59
      68      59
   }

   method 'testFinally4 (Ljava/util/function/Supplier;)Z' {
      0      64
      1      64
      2      67
      3      67
      4      67
      5      67
      6      67
      7      67
      b      67
      c      67
      d      67
      e      67
      1b      69
      1c      69
      1d      69
      1e      69
      1f      69
      20      69
      21      69
      22      69
      25      72
      26      72
   }

   method 'testFinally5 (Ljava/util/function/Supplier;)Z' {
      0      76
      1      76
      2      79
      3      79
      4      79
      5      79
      6      79
      7      79
      b      79
      c      79
      d      79
      e      79
      1a      80
      1b      81
      1c      81
      1d      81
      1e      81
      1f      81
      20      81
      21      81
      22      81
      23      82
      24      82
      25      82
      26      82
      27      82
      28      82
      2c      82
      2d      82
      2e      82
      2f      82
      3d      84
      3e      84
      3f      84
      40      84
      41      84
      42      84
      43      84
      44      84
      48      87
      49      87
   }

   method 'testFinally6 (ZLjava/util/function/Supplier;)Z' {
      0      91
      1      91
      2      94
      3      94
      4      94
      5      94
      6      95
      7      95
      8      96
      9      96
      a      96
      b      96
      c      96
      d      96
      e      96
      f      96
      10      99
      11      99
      12      99
      13      99
      14      99
      15      99
      19      99
      1a      99
      1b      99
      1c      99
      28      100
      2a      101
      2b      101
      2c      101
      2d      101
      2e      101
      2f      101
      30      101
      31      101
      32      102
      33      102
      34      102
      35      102
      36      102
      37      102
      3b      102
      3c      102
      3d      102
      3e      102
      4c      104
      4d      104
      4e      104
      4f      104
      50      104
      51      104
      52      104
      53      104
      57      107
      58      107
   }

   method 'testLoopFinally ()V' {
      0      111
      1      111
      2      115
      3      115
      4      115
      5      115
      e      116
      1b      119
      1c      119
      1d      119
      1e      119
      1f      119
      20      119
      21      119
      22      119
   }

   method 'testPostdomFailure ()V' {
      0      190
      1      190
      2      190
      3      190
      4      190
      5      190
      6      190
      e      192
      f      192
      10      192
      14      195
      15      195
      16      195
      17      195
      18      195
      19      195
      1a      195
      21      196
      22      197
      23      197
      24      197
      25      197
      26      197
      27      197
      28      197
      3a      202
      3b      202
      3c      202
      3d      202
      41      205
   }

   method 'testVarWrong ()V' {
      0      209
      1      209
      2      209
      3      209
      4      209
      5      209
      6      209
      7      209
      e      211
      f      212
      10      212
      11      212
      12      212
      16      219
      17      213
      18      213
      19      213
      1a      213
      1b      213
      1c      213
      1d      213
      21      214
      24      217
      25      217
      26      217
      27      217
      2b      210
   }

   method 'testInvalidUse ()V' {
      0      222
      1      222
      2      223
      3      223
      4      223
      5      228
      6      228
      7      228
      8      228
      9      228
      a      228
      b      228
      13      229
      14      230
      15      235
      16      235
      17      235
      18      235
      19      235
      1a      235
      1b      235
      26      237
      36      244
      39      239
      3a      239
      3b      239
      3c      239
      3d      239
      3e      239
      3f      239
      4f      242
      50      242
      51      242
      52      242
      53      242
      54      242
      55      242
      59      236
   }

   method 'returnInCatch ()V' {
      0      249
      1      249
      2      249
      3      249
      4      249
      5      249
      6      249
      7      249
      13      251
      14      252
      15      252
      16      252
      17      252
      18      252
      19      252
      1a      252
      1b      252
      24      257
      26      254
      27      254
      28      254
      29      254
      2a      254
      2b      254
      2c      254
      2d      254
      30      260
      31      260
      32      260
      33      260
      34      260
      35      260
      36      260
      37      260
      38      261
   }
}

Lines mapping:
9 <-> 9
10 <-> 10
11 <-> 11
17 <-> 17
19 <-> 19
24 <-> 24
27 <-> 28
28 <-> 35
31 <-> 32
34 <-> 38
35 <-> 39
40 <-> 44
42 <-> 46
45 <-> 49
50 <-> 54
51 <-> 57
54 <-> 55
55 <-> 55
58 <-> 55
60 <-> 60
65 <-> 65
67 <-> 68
69 <-> 70
72 <-> 73
76 <-> 77
78 <-> 80
79 <-> 81
80 <-> 82
81 <-> 83
83 <-> 85
86 <-> 88
90 <-> 92
92 <-> 95
93 <-> 96
94 <-> 97
97 <-> 100
98 <-> 101
99 <-> 102
100 <-> 103
102 <-> 105
105 <-> 108
109 <-> 112
113 <-> 116
114 <-> 117
117 <-> 120
155 <-> 191
157 <-> 193
160 <-> 196
161 <-> 197
162 <-> 198
168 <-> 203
171 <-> 206
176 <-> 210
177 <-> 212
178 <-> 213
179 <-> 220
181 <-> 214
182 <-> 215
185 <-> 218
187 <-> 211
190 <-> 223
191 <-> 224
193 <-> 229
194 <-> 230
195 <-> 231
197 <-> 236
198 <-> 238
199 <-> 245
202 <-> 240
206 <-> 243
208 <-> 237
212 <-> 250
213 <-> 252
214 <-> 253
215 <-> 258
217 <-> 255
220 <-> 261
221 <-> 262
Not mapped:
20
32
43
61
70
84
103
118
165
169
186
203
207
218
