package pkg;

public class TestLoopFinally {
   public void test() {
      for(int i = 0; i < 10; ++i) {// 5 16
         try {
            System.out.println(i);// 7
         } finally {
            System.out.println("finally");// 9
            if (i == 5) {// 11
               break;
            }

            System.out.println("finally2");// 15
         }
      }

      System.out.println("after");// 19
   }// 20

   public void test1() {
      for(int i = 0; i < 10; ++i) {// 23
         try {
            System.out.println(i);// 25
         } finally {
            System.out.println("finally");// 27
            if (i != 5) {// 29
               if (i == 4) {// 32
                  System.out.println("break");// 33
                  break;// 34
               }

               System.out.println("finally2");// 37
            }

            System.out.println("continue");// 30
            continue;// 31
         }
      }

      System.out.println("after");// 41
   }// 42

   public void test2() {
      for(int i = 0; i < 10; ++i) {// 45
         try {
            System.out.println(i);// 47
         } finally {
            System.out.println("finally");// 49
            if (i != 5) {// 51
               continue;
            }
            break;
         }
      }

      System.out.println("after");// 59
   }// 60

   public int test3(int param1) {
      // $FF: Couldn't be decompiled
      // Bytecode:
      // 00: iload 1
      // 01: bipush 1
      // 02: if_icmpne 11
      // 05: bipush 1
      // 06: istore 2
      // 07: iload 1
      // 08: bipush 3
      // 09: if_icmpne 0f
      // 0c: goto 5e
      // 0f: iload 2
      // 10: ireturn
      // 11: getstatic java/lang/System.out Ljava/io/PrintStream;
      // 14: ldc "Oops"
      // 16: invokevirtual java/io/PrintStream.println (Ljava/lang/String;)V
      // 19: iload 1
      // 1a: bipush 23
      // 1c: if_icmpne 2b
      // 1f: bipush 1
      // 20: istore 2
      // 21: iload 1
      // 22: bipush 3
      // 23: if_icmpne 29
      // 26: goto 5e
      // 29: iload 2
      // 2a: ireturn
      // 2b: getstatic java/lang/System.out Ljava/io/PrintStream;
      // 2e: ldc "Oops"
      // 30: invokevirtual java/io/PrintStream.println (Ljava/lang/String;)V
      // 33: iload 1
      // 34: bipush 25
      // 36: if_icmpne 45
      // 39: bipush 1
      // 3a: istore 2
      // 3b: iload 1
      // 3c: bipush 3
      // 3d: if_icmpne 43
      // 40: goto 5e
      // 43: iload 2
      // 44: ireturn
      // 45: iload 1
      // 46: bipush 3
      // 47: if_icmpne 58
      // 4a: goto 5e
      // 4d: astore 3
      // 4e: iload 1
      // 4f: bipush 3
      // 50: if_icmpne 56
      // 53: goto 5e
      // 56: aload 3
      // 57: athrow
      // 58: iload 1
      // 59: bipush 45
      // 5b: if_icmplt 00
      // 5e: getstatic java/lang/System.out Ljava/io/PrintStream;
      // 61: bipush 5
      // 62: invokevirtual java/io/PrintStream.print (I)V
      // 65: bipush 1
      // 66: ireturn
   }
}

class 'pkg/TestLoopFinally' {
   method 'test ()V' {
      0      4
      1      4
      2      4
      3      4
      4      4
      5      4
      8      6
      9      6
      a      6
      b      6
      c      6
      27      4
      2a      8
      2b      8
      2c      8
      2d      8
      2e      8
      2f      8
      30      9
      31      9
      32      9
      33      9
      34      9
      3b      13
      3c      13
      3d      13
      3e      13
      3f      13
      40      13
      41      13
      42      13
      4b      17
      4c      17
      4d      17
      4e      17
      4f      17
      50      17
      51      17
      52      17
      53      18
   }

   method 'test1 ()V' {
      0      21
      1      21
      2      21
      3      21
      4      21
      5      21
      8      23
      9      23
      a      23
      b      23
      c      23
      42      25
      43      25
      44      25
      45      25
      46      25
      47      25
      48      26
      49      26
      4a      26
      4b      26
      4c      26
      50      35
      51      35
      52      35
      53      35
      54      35
      55      35
      56      35
      57      35
      58      36
      5b      27
      5c      27
      5d      27
      60      28
      61      28
      62      28
      63      28
      64      28
      65      28
      66      28
      67      28
      68      29
      6b      32
      6c      32
      6d      32
      6e      32
      6f      32
      70      32
      71      32
      72      32
      75      21
      76      21
      77      21
      7b      40
      7c      40
      7d      40
      7e      40
      7f      40
      80      40
      81      40
      82      40
      83      41
   }

   method 'test2 ()V' {
      0      44
      1      44
      2      44
      3      44
      4      44
      5      44
      8      46
      9      46
      a      46
      b      46
      c      46
      1f      48
      20      48
      21      48
      22      48
      23      48
      24      48
      25      49
      26      49
      27      49
      28      49
      29      49
      30      44
      31      44
      32      44
      36      56
      37      56
      38      56
      39      56
      3a      56
      3b      56
      3c      56
      3d      56
      3e      57
   }
}

Lines mapping:
5 <-> 5
7 <-> 7
9 <-> 9
11 <-> 10
15 <-> 14
16 <-> 5
19 <-> 18
20 <-> 19
23 <-> 22
25 <-> 24
27 <-> 26
29 <-> 27
30 <-> 36
31 <-> 37
32 <-> 28
33 <-> 29
34 <-> 30
37 <-> 33
41 <-> 41
42 <-> 42
45 <-> 45
47 <-> 47
49 <-> 49
51 <-> 50
59 <-> 57
60 <-> 58
Not mapped:
12
38
52
