package pkg;

public class TestSwitchPatternMatching18 {
   static void test(Integer param0) {
      // $VF: Couldn't be decompiled
      // Bytecode:
      // 00: aload 0
      // 01: dup
      // 02: invokestatic java/util/Objects.requireNonNull (Ljava/lang/Object;)Ljava/lang/Object;
      // 05: pop
      // 06: astore 1
      // 07: bipush 0
      // 08: istore 2
      // 09: aload 1
      // 0a: iload 2
      // 0b: invokedynamic typeSwitch (Ljava/lang/Object;I)I bsm=java/lang/runtime/SwitchBootstraps.typeSwitch (Ljava/lang/invoke/MethodHandles$Lookup;Ljava/lang/String;Ljava/lang/invoke/MethodType;[Ljava/lang/Object;)Ljava/lang/invoke/CallSite; args=[ 42, java/lang/Integer, java/lang/Integer ]
      // 10: tableswitch 100 0 2 28 39 66
      // 2c: getstatic java/lang/System.out Ljava/io/PrintStream;
      // 2f: ldc "42"
      // 31: invokevirtual java/io/PrintStream.println (Ljava/lang/String;)V
      // 34: goto 7f
      // 37: aload 1
      // 38: astore 3
      // 39: aload 3
      // 3a: invokevirtual java/lang/Integer.intValue ()I
      // 3d: bipush 50
      // 3f: if_icmplt 47
      // 42: bipush 2
      // 43: istore 2
      // 44: goto 09
      // 47: getstatic java/lang/System.out Ljava/io/PrintStream;
      // 4a: ldc "small"
      // 4c: invokevirtual java/io/PrintStream.println (Ljava/lang/String;)V
      // 4f: goto 7f
      // 52: aload 1
      // 53: astore 4
      // 55: aload 4
      // 57: bipush 17
      // 59: invokestatic java/lang/Integer.valueOf (I)Ljava/lang/Integer;
      // 5c: invokeinterface java/lang/Comparable.compareTo (Ljava/lang/Object;)I 2
      // 61: ifgt 69
      // 64: bipush 3
      // 65: istore 2
      // 66: goto 09
      // 69: getstatic java/lang/System.out Ljava/io/PrintStream;
      // 6c: ldc "comparable"
      // 6e: invokevirtual java/io/PrintStream.println (Ljava/lang/String;)V
      // 71: goto 7f
      // 74: getstatic java/lang/System.out Ljava/io/PrintStream;
      // 77: ldc "default"
      // 79: invokevirtual java/io/PrintStream.println (Ljava/lang/String;)V
      // 7c: goto 7f
      // 7f: return
   }

   // $VF: Could not properly define all variable types!
   static void test2(Integer o) {
      Integer i = o;// 16
      <unknown> var3;
      switch (i) {
         case 16:
         case null:
            System.out.println("maybe 16?");// 18
            break;
         case 42:
            System.out.println("42");// 17
            break;
         case Integer var4 when var3 < 50:// 19
            System.out.println("small");
            break;
         default:
            System.out.println("default");// 20
      }
   }// 22

   // $VF: Could not properly define all variable types!
   static void test3(Integer o) {
      Integer i = o;// 25
      <unknown> var3;
      switch (i) {
         case 16:
         case null:
            System.out.println("definitely null");// 29
            break;
         case 42:
            System.out.println("42");// 26
            break;
         case Integer var4 when var3 < 50:// 27
            System.out.println("small");
            break;
         default:
            System.out.println("default");// 30
      }
   }// 32
}

class 'pkg/TestSwitchPatternMatching18' {
   method 'test2 (Ljava/lang/Integer;)V' {
      0      57
      1      57
      4      59
      b      59
      c      59
      d      59
      e      59
      f      59
      10      59
      11      59
      12      59
      13      59
      14      59
      15      59
      16      59
      17      59
      18      59
      19      59
      1a      59
      1b      59
      1c      59
      1d      59
      1e      59
      1f      59
      20      59
      21      59
      22      59
      23      59
      24      59
      25      59
      26      59
      27      59
      28      65
      29      65
      2a      65
      2b      65
      2c      65
      2d      65
      2e      65
      2f      65
      30      66
      33      62
      34      62
      35      62
      36      62
      37      62
      38      62
      39      62
      3a      62
      3b      63
      40      67
      41      67
      42      67
      43      67
      44      67
      45      67
      46      67
      47      67
      48      67
      4e      68
      4f      68
      50      68
      51      68
      52      68
      53      68
      54      68
      55      68
      56      69
      59      71
      5a      71
      5b      71
      5c      71
      5d      71
      5e      71
      5f      71
      60      71
      64      73
   }

   method 'test3 (Ljava/lang/Integer;)V' {
      0      77
      1      77
      4      79
      b      79
      c      79
      d      79
      e      79
      f      79
      10      79
      11      79
      12      79
      13      79
      14      79
      15      79
      16      79
      17      79
      18      79
      19      79
      1a      79
      1b      79
      1c      79
      1d      79
      1e      79
      1f      79
      20      79
      21      79
      22      79
      23      79
      24      79
      25      79
      26      79
      27      79
      28      85
      29      85
      2a      85
      2b      85
      2c      85
      2d      85
      2e      85
      2f      85
      30      86
      35      87
      36      87
      37      87
      38      87
      39      87
      3a      87
      3b      87
      3c      87
      3d      87
      43      88
      44      88
      45      88
      46      88
      47      88
      48      88
      49      88
      4a      88
      4b      89
      4e      82
      4f      82
      50      82
      51      82
      52      82
      53      82
      54      82
      55      82
      56      83
      59      91
      5a      91
      5b      91
      5c      91
      5d      91
      5e      91
      5f      91
      60      91
      64      93
   }
}

Lines mapping:
16 <-> 58
17 <-> 66
18 <-> 63
19 <-> 68
20 <-> 72
22 <-> 74
25 <-> 78
26 <-> 86
27 <-> 88
29 <-> 83
30 <-> 92
32 <-> 94
