package pkg;

import java.io.File;
import java.io.FileNotFoundException;
import java.util.Scanner;

public class TestTryWithResourcesReturnJ16 {
   public Scanner test(File file) throws FileNotFoundException {
      Scanner var3;
      try (Scanner scanner = new Scanner(file)) {// 9
         var3 = scanner;
      }

      return var3;// 10
   }

   public Scanner testFunc(File file) throws FileNotFoundException {
      Scanner var3;
      try (Scanner scanner = this.create(file)) {// 15
         var3 = scanner;
      }

      return var3;// 16
   }

   public Scanner testFinally(File file) {
      try {
         try (Scanner scanner = new Scanner(file)) {// 21
            ;
         }

         return null;// 24
      } finally {
         ;
      }
   }

   public Scanner testFinallyNested(File param1) {
      // $FF: Couldn't be decompiled
      // Bytecode:
      // 00: new java/util/Scanner
      // 03: dup
      // 04: aload 1
      // 05: invokespecial java/util/Scanner.<init> (Ljava/io/File;)V
      // 08: astore 2
      // 09: new java/util/Scanner
      // 0c: dup
      // 0d: aload 1
      // 0e: invokespecial java/util/Scanner.<init> (Ljava/io/File;)V
      // 11: astore 3
      // 12: aload 3
      // 13: astore 4
      // 15: aload 3
      // 16: invokevirtual java/util/Scanner.close ()V
      // 19: aload 2
      // 1a: astore 5
      // 1c: aload 2
      // 1d: invokevirtual java/util/Scanner.close ()V
      // 20: aconst_null
      // 21: areturn
      // 22: astore 4
      // 24: aload 3
      // 25: invokevirtual java/util/Scanner.close ()V
      // 28: goto 34
      // 2b: astore 5
      // 2d: aload 4
      // 2f: aload 5
      // 31: invokevirtual java/lang/Throwable.addSuppressed (Ljava/lang/Throwable;)V
      // 34: aload 4
      // 36: athrow
      // 37: astore 6
      // 39: aload 2
      // 3a: astore 7
      // 3c: aload 2
      // 3d: invokevirtual java/util/Scanner.close ()V
      // 40: aconst_null
      // 41: areturn
      // 42: astore 3
      // 43: aload 2
      // 44: invokevirtual java/util/Scanner.close ()V
      // 47: goto 52
      // 4a: astore 4
      // 4c: aload 3
      // 4d: aload 4
      // 4f: invokevirtual java/lang/Throwable.addSuppressed (Ljava/lang/Throwable;)V
      // 52: aload 3
      // 53: athrow
      // 54: astore 8
      // 56: aconst_null
      // 57: areturn
   }

   public String testComplex(File f, File f2, File f3) throws FileNotFoundException {
      Scanner scanner = this.create(f);

      String o;
      label104: {
         Object var16;
         try {
            Scanner s2 = this.create(f2);// 43

            label106: {
               try {
                  scanner.next();// 44
                  if (!scanner.hasNext() || !s2.hasNext()) {// 46
                     var16 = null;
                     break label106;
                  }

                  try (Scanner s = this.create(f3)) {// 50
                     scanner.next();// 51

                     for(int i = 0; i < s.nextInt(); ++i) {// 53
                        System.out.println(i);// 54
                     }

                     o = s.next();// 57
                  }
               } catch (Throwable var14) {
                  if (s2 != null) {
                     try {
                        s2.close();
                     } catch (Throwable var11) {
                        var14.addSuppressed(var11);
                     }
                  }

                  throw var14;
               }

               if (s2 != null) {
                  s2.close();
               }
               break label104;
            }

            if (s2 != null) {
               s2.close();
            }
         } catch (Throwable var15) {// 42
            if (scanner != null) {
               try {
                  scanner.close();
               } catch (Throwable var10) {
                  var15.addSuppressed(var10);
               }
            }

            throw var15;
         }

         if (scanner != null) {
            scanner.close();
         }

         return (String)var16;// 47
      }

      if (scanner != null) {// 59
         scanner.close();
      }

      return o;// 61
   }

   public String testComplex1(File f, File f2, File f3) throws FileNotFoundException {
      Scanner scanner = this.create(f);

      String var6;
      label74: {
         try {
            Scanner s2 = this.create(f2);// 66

            label76: {
               try {
                  if (!scanner.hasNext() || !s2.hasNext()) {// 67
                     s2.next();// 71
                     break label76;
                  }

                  var6 = scanner.next();
               } catch (Throwable var10) {
                  if (s2 != null) {
                     try {
                        s2.close();
                     } catch (Throwable var9) {
                        var10.addSuppressed(var9);
                     }
                  }

                  throw var10;
               }

               if (s2 != null) {
                  s2.close();
               }
               break label74;
            }

            if (s2 != null) {
               s2.close();
            }
         } catch (Throwable var11) {// 65
            if (scanner != null) {
               try {
                  scanner.close();
               } catch (Throwable var8) {
                  var11.addSuppressed(var8);
               }
            }

            throw var11;
         }

         if (scanner != null) {// 72
            scanner.close();
         }

         return null;// 74
      }

      if (scanner != null) {
         scanner.close();
      }

      return var6;// 68
   }

   public String testComplex2(File f, File f2, File f3) throws FileNotFoundException {
      Scanner scanner = this.create(f);

      String var5;
      label43: {
         try {
            if (scanner.hasNext()) {// 79
               var5 = scanner.next();
               break label43;
            }

            scanner.next();// 83
         } catch (Throwable var8) {// 78
            if (scanner != null) {
               try {
                  scanner.close();
               } catch (Throwable var7) {
                  var8.addSuppressed(var7);
               }
            }

            throw var8;
         }

         if (scanner != null) {// 84
            scanner.close();
         }

         return null;// 86
      }

      if (scanner != null) {
         scanner.close();
      }

      return var5;// 80
   }

   private Scanner create(File file) throws FileNotFoundException {
      return new Scanner(file);// 90
   }
}

class 'pkg/TestTryWithResourcesReturnJ16' {
   method 'test (Ljava/io/File;)Ljava/util/Scanner;' {
      4      9
      8      9
      9      10
      a      10
      f      13
      10      13
   }

   method 'testFunc (Ljava/io/File;)Ljava/util/Scanner;' {
      0      18
      1      18
      2      18
      3      18
      4      18
      5      18
      6      19
      7      19
      10      22
      11      22
   }

   method 'testFinally (Ljava/io/File;)Ljava/util/Scanner;' {
      4      27
      8      27
      f      31
      10      31
   }

   method 'testComplex (Ljava/io/File;Ljava/io/File;Ljava/io/File;)Ljava/lang/String;' {
      0      93
      1      93
      2      93
      3      93
      4      93
      5      93
      6      93
      7      99
      8      99
      9      99
      a      99
      b      99
      c      99
      d      99
      e      103
      f      103
      10      103
      11      103
      12      103
      14      104
      15      104
      16      104
      17      104
      18      104
      19      104
      1c      104
      1d      104
      1e      104
      1f      104
      20      104
      21      104
      24      105
      25      105
      26      105
      27      136
      28      136
      29      136
      2c      137
      2d      137
      2e      137
      31      151
      32      151
      33      151
      36      152
      37      152
      38      152
      3b      155
      3c      155
      3d      155
      3e      109
      3f      109
      40      109
      41      109
      42      109
      43      109
      44      109
      45      110
      46      110
      47      110
      48      110
      49      110
      4b      112
      4c      112
      4d      112
      4e      112
      4f      112
      50      112
      51      112
      52      112
      53      112
      54      112
      55      112
      58      113
      59      113
      5a      113
      5b      113
      5c      113
      5d      113
      5e      113
      5f      113
      60      112
      61      112
      62      112
      66      116
      67      116
      68      116
      69      116
      6a      116
      6b      116
      6c      116
      95      130
      96      130
      97      130
      9a      131
      9b      131
      9c      131
      9d      131
      9e      131
      a2      118
      a4      119
      a5      119
      a6      119
      a9      121
      aa      121
      ab      121
      b1      122
      b7      123
      bc      127
      bd      158
      be      158
      bf      158
      c2      159
      c3      159
      c4      159
      c5      159
      c6      159
      ca      139
      cc      140
      cd      140
      ce      140
      d1      142
      d2      142
      d3      142
      d9      143
      df      144
      e4      148
      e5      162
      e6      162
      e7      162
   }

   method 'testComplex1 (Ljava/io/File;Ljava/io/File;Ljava/io/File;)Ljava/lang/String;' {
      0      166
      1      166
      2      166
      3      166
      4      166
      5      166
      6      166
      7      171
      8      171
      9      171
      a      171
      b      171
      c      171
      d      171
      e      175
      f      175
      10      175
      11      175
      12      175
      13      175
      16      175
      17      175
      18      175
      19      175
      1a      175
      1b      175
      1e      180
      1f      180
      20      180
      21      180
      22      180
      23      180
      24      180
      25      193
      26      193
      27      193
      2a      194
      2b      194
      2c      194
      2f      221
      30      221
      31      221
      34      222
      35      222
      36      222
      39      225
      3a      225
      3b      225
      3c      176
      3d      176
      3e      176
      3f      176
      40      176
      42      199
      43      199
      44      199
      47      200
      48      200
      49      200
      4a      200
      4b      200
      4f      181
      51      182
      52      182
      53      182
      56      184
      57      184
      58      184
      5e      185
      64      186
      69      190
      6a      214
      6b      214
      6c      214
      6f      215
      70      215
      71      215
      72      215
      73      215
      77      202
      79      203
      7a      203
      7b      203
      7e      205
      7f      205
      80      205
      86      206
      8c      207
      91      211
      92      218
      93      218
   }

   method 'testComplex2 (Ljava/io/File;Ljava/io/File;Ljava/io/File;)Ljava/lang/String;' {
      0      229
      1      229
      2      229
      3      229
      4      229
      5      229
      6      229
      7      234
      8      234
      9      234
      a      234
      b      234
      c      234
      f      235
      10      235
      11      235
      12      235
      13      235
      14      235
      15      235
      16      259
      17      259
      18      259
      1b      260
      1c      260
      1d      260
      20      263
      21      263
      22      263
      23      239
      24      239
      25      239
      26      239
      27      239
      29      252
      2a      252
      2b      252
      2e      253
      2f      253
      30      253
      31      253
      32      253
      36      240
      38      241
      39      241
      3a      241
      3d      243
      3e      243
      3f      243
      45      244
      4b      245
      50      249
      51      256
      52      256
   }

   method 'create (Ljava/io/File;)Ljava/util/Scanner;' {
      4      267
      8      267
   }
}

Lines mapping:
9 <-> 10
10 <-> 14
15 <-> 19
16 <-> 23
21 <-> 28
24 <-> 32
42 <-> 140
43 <-> 100
44 <-> 104
46 <-> 105
47 <-> 156
50 <-> 110
51 <-> 111
53 <-> 113
54 <-> 114
57 <-> 117
59 <-> 159
61 <-> 163
65 <-> 203
66 <-> 172
67 <-> 176
68 <-> 226
71 <-> 177
72 <-> 215
74 <-> 219
78 <-> 241
79 <-> 235
80 <-> 264
83 <-> 240
84 <-> 253
86 <-> 257
90 <-> 268
Not mapped:
11
17
22
23
58
