package pkg;

public class TestSynchronized {
   public void test1() {
      synchronized(this) {// 5
         ;
      }
   }// 8

   public void test2() {
      synchronized(new Object()) {// 11
         ;
      }
   }// 14

   public void test3() {
      Object o;
      synchronized(new Object()) {// 18
         o = new Object();// 19
         System.out.println(o);// 20
      }// 21

      System.out.println(o);// 22
   }// 23

   public void test4() {
      Integer o;
      synchronized(1) {// 27
         o = 1;// 28
         System.out.println(o);// 29
      }// 30

      System.out.println(o);// 31
   }// 32

   public void test5(int param1) {
      // $FF: Couldn't be decompiled
      // java.lang.RuntimeException: parsing failure!
      //   at org.jetbrains.java.decompiler.modules.decompiler.DomHelper.parseGraph(DomHelper.java:213)
      //   at org.jetbrains.java.decompiler.main.rels.MethodProcessorRunnable.codeToJava(MethodProcessorRunnable.java:128)
      //
      // Bytecode:
      // 00: aload 0
      // 01: dup
      // 02: astore 2
      // 03: monitorenter
      // 04: iload 1
      // 05: iload 1
      // 06: if_icmplt 10
      // 09: aload 0
      // 0a: invokevirtual java/lang/Object.wait ()V
      // 0d: goto 04
      // 10: aload 2
      // 11: monitorexit
      // 12: goto 1a
      // 15: astore 3
      // 16: aload 2
      // 17: monitorexit
      // 18: aload 3
      // 19: athrow
      // 1a: aload 0
      // 1b: dup
      // 1c: astore 2
      // 1d: monitorenter
      // 1e: aload 0
      // 1f: invokevirtual java/lang/Object.notifyAll ()V
      // 22: aload 2
      // 23: monitorexit
      // 24: goto 2e
      // 27: astore 4
      // 29: aload 2
      // 2a: monitorexit
      // 2b: aload 4
      // 2d: athrow
      // 2e: goto 00
      // 31: astore 2
      // 32: new java/lang/RuntimeException
      // 35: dup
      // 36: aload 2
      // 37: invokespecial java/lang/RuntimeException.<init> (Ljava/lang/Throwable;)V
      // 3a: athrow
   }
}

class 'pkg/TestSynchronized' {
   method 'test1 ()V' {
      0      4
      3      4
      e      7
   }

   method 'test2 ()V' {
      9      10
      14      13
   }

   method 'test3 ()V' {
      b      17
      13      18
      14      19
      15      19
      16      19
      17      19
      18      19
      19      19
      1a      19
      1c      20
      25      22
      26      22
      27      22
      28      22
      29      22
      2a      22
      2b      22
      2c      23
   }

   method 'test4 ()V' {
      0      27
      1      27
      2      27
      3      27
      8      27
      9      28
      a      28
      b      28
      c      28
      d      28
      e      29
      f      29
      10      29
      11      29
      12      29
      13      29
      14      29
      16      30
      1f      32
      20      32
      21      32
      22      32
      23      32
      24      32
      25      32
      26      33
   }
}

Lines mapping:
5 <-> 5
8 <-> 8
11 <-> 11
14 <-> 14
18 <-> 18
19 <-> 19
20 <-> 20
21 <-> 21
22 <-> 23
23 <-> 24
27 <-> 28
28 <-> 29
29 <-> 30
30 <-> 31
31 <-> 33
32 <-> 34
Not mapped:
7
13
37
38
39
41
43
44
45
47
48
