/**
 * This code can be assembled with <a href="https://wiki.openjdk.java.net/display/CodeTools/asmtools">asmtools</a>
 * using <code>asmtools jasm -g *.jasm</code> command line.
 */
package  pkg;

super public class TestMissingLambdaBody
  version 52:0
{
  // weird fix
  const #1 = Method TestMissingLambdaBody.lambda$init$0:"(Ljava/lang/Integer;)V";

  public Method "<init>":"()V"
  stack 1 locals 1
  {
    aload_0;
    invokespecial  Method java/lang/Object."<init>":"()V";
    return;
  
  }
  public Method init:"()V"
  stack 2 locals 1
  {
    aload_0;
    aload_0;
    invokedynamic  InvokeDynamic REF_invokeStatic:Method java/lang/invoke/LambdaMetafactory.metafactory:"(Ljava/lang/invoke/MethodHandles$Lookup;Ljava/lang/String;Ljava/lang/invoke/MethodType;Ljava/lang/invoke/MethodType;Ljava/lang/invoke/MethodHandle;Ljava/lang/invoke/MethodType;)Ljava/lang/invoke/CallSite;":accept:"(Lpkg/TestMissingLambdaBody;)Ljava/util/function/Consumer;" {
      MethodType "(Ljava/lang/Object;)V",
      MethodHandle REF_invokeVirtual:#1,
      MethodType "(Ljava/lang/Integer;)V"
    };
    invokevirtual  Method visit:"(Ljava/util/function/Consumer;)V";
    return;
  
  }
  public Method visit:"(Ljava/util/function/Consumer;)V"
  stack 2 locals 2
  {
    aload_1;
    ldc  String "Foo";
    invokevirtual  Method java/lang/String.hashCode:"()I";
    invokestatic  Method java/lang/Integer.valueOf:"(I)Ljava/lang/Integer;";
    invokeinterface  InterfaceMethod java/util/function/Consumer.accept:"(Ljava/lang/Object;)V",  2;
    aload_1;
    ldc  String "Bar";
    invokevirtual  Method java/lang/String.length:"()I";
    invokestatic  Method java/lang/Integer.valueOf:"(I)Ljava/lang/Integer;";
    invokeinterface  InterfaceMethod java/util/function/Consumer.accept:"(Ljava/lang/Object;)V",  2;
    return;
  
  }
  public Method accept:"(Ljava/lang/Number;)Ljava/lang/Number;"
  stack 2 locals 2
  {
    getstatic  Field java/lang/System.out:"Ljava/io/PrintStream;";
    aload_1;
    invokevirtual  Method java/io/PrintStream.println:"(Ljava/lang/Object;)V";
    aload_1;
    areturn;
  
  }
  private synthetic Method lambda$init$0:"(Ljava/lang/Integer;)V"
  stack 2 locals 2
  {
    aload_0;
    aload_1;
    invokevirtual  Method accept:"(Ljava/lang/Number;)Ljava/lang/Number;";
    checkcast java/lang/Integer; // No idea why javac would compile this checkcast
    pop;
    return;
  
  }

  public static final InnerClass Lookup=class java/lang/invoke/MethodHandles$Lookup of class java/lang/invoke/MethodHandles;

} // end Class TestMissingLambdaBody
